README.md
setup.cfg
setup.py
rumetr/__init__.py
rumetr/exceptions.py
rumetr/roometr.py
rumetr/scrapy/__init__.py
rumetr/scrapy/cian.py
rumetr/scrapy/item.py
rumetr/scrapy/pipeline.py
rumetr/scrapy/yandex.py
rumetr/tests/__init__.py
rumetr/tests/test_appt_list.py
rumetr/tests/test_appts.py
rumetr/tests/test_complexes.py
rumetr/tests/test_decimal.py
rumetr/tests/test_developers.py
rumetr/tests/test_houses.py
rumetr/tests/test_http.py
rumetr/tests/test_scrapy_pipeline.py
rumetr_client.egg-info/PKG-INFO
rumetr_client.egg-info/SOURCES.txt
rumetr_client.egg-info/dependency_links.txt
rumetr_client.egg-info/not-zip-safe
rumetr_client.egg-info/requires.txt
rumetr_client.egg-info/top_level.txt