Metadata-Version: 1.0
Name: rumetr-client
Version: 0.2.4
Summary: Client for rumetr.com API
Home-page: https://github.com/f213/rumetr-client/
Author: Fedor Borshev
Author-email: f@f213.in
License: MIT
Platform: UNKNOWN
